JavaguideMianshiTujiBanFix1/README.md
JavaguideMianshiTujiBanFix1/__init__.py
JavaguideMianshiTujiBanFix1/__main__.py
JavaguideMianshiTujiBanFix1/file.epub
JavaguideMianshiTujiBanFix1/index.html
JavaguideMianshiTujiBanFix1/css/__init__.py
JavaguideMianshiTujiBanFix1/css/annotations.css
JavaguideMianshiTujiBanFix1/css/main.css
JavaguideMianshiTujiBanFix1/css/normalize.css
JavaguideMianshiTujiBanFix1/css/popup.css
JavaguideMianshiTujiBanFix1/font/__init__.py
JavaguideMianshiTujiBanFix1/font/fontello.eot
JavaguideMianshiTujiBanFix1/font/fontello.svg
JavaguideMianshiTujiBanFix1/font/fontello.ttf
JavaguideMianshiTujiBanFix1/font/fontello.woff
JavaguideMianshiTujiBanFix1/img/__init__.py
JavaguideMianshiTujiBanFix1/img/annotator-glyph-sprite.png
JavaguideMianshiTujiBanFix1/img/annotator-icon-sprite.png
JavaguideMianshiTujiBanFix1/img/apple-touch-icon.png
JavaguideMianshiTujiBanFix1/img/cancelfullscreen.png
JavaguideMianshiTujiBanFix1/img/close.png
JavaguideMianshiTujiBanFix1/img/fullscreen.png
JavaguideMianshiTujiBanFix1/img/loader.gif
JavaguideMianshiTujiBanFix1/img/menu-icon.png
JavaguideMianshiTujiBanFix1/img/save.png
JavaguideMianshiTujiBanFix1/img/saved.png
JavaguideMianshiTujiBanFix1/img/settings-s.png
JavaguideMianshiTujiBanFix1/img/settings.png
JavaguideMianshiTujiBanFix1/img/star.png
JavaguideMianshiTujiBanFix1/js/__init__.py
JavaguideMianshiTujiBanFix1/js/epub.js
JavaguideMianshiTujiBanFix1/js/epub.min.js
JavaguideMianshiTujiBanFix1/js/epub.min.map
JavaguideMianshiTujiBanFix1/js/hooks.min.js
JavaguideMianshiTujiBanFix1/js/hooks.min.map
JavaguideMianshiTujiBanFix1/js/reader.js
JavaguideMianshiTujiBanFix1/js/reader.js.map
JavaguideMianshiTujiBanFix1/js/reader.min.js
JavaguideMianshiTujiBanFix1/js/reader.min.map
JavaguideMianshiTujiBanFix1/js/hooks/__init__.py
JavaguideMianshiTujiBanFix1/js/hooks/extensions/__init__.py
JavaguideMianshiTujiBanFix1/js/hooks/extensions/highlight.js
JavaguideMianshiTujiBanFix1/js/libs/__init__.py
javaguide_mianshi_tuji_ban_fix1-2025.3.24.1.dist-info/METADATA
javaguide_mianshi_tuji_ban_fix1-2025.3.24.1.dist-info/WHEEL
javaguide_mianshi_tuji_ban_fix1-2025.3.24.1.dist-info/entry_points.txt
javaguide_mianshi_tuji_ban_fix1-2025.3.24.1.dist-info/top_level.txt
javaguide_mianshi_tuji_ban_fix1-2025.3.24.1.dist-info/RECORD
